{
  "topic": {
    "tags": [],
    "tags_descriptions": {},
    "fancy_title": "OAuth 2.1",
    "id": 346,
    "title": "OAuth 2.1",
    "posts_count": 2,
    "created_at": "2026-01-07T15:46:54.699Z",
    "views": 1,
    "reply_count": 0,
    "like_count": 0,
    "last_posted_at": "2026-01-07T16:27:17.047Z",
    "visible": true,
    "closed": false,
    "archived": false,
    "archetype": "regular",
    "slug": "oauth-2-1",
    "category_id": 44,
    "word_count": 559,
    "deleted_at": null,
    "user_id": 1,
    "featured_link": null,
    "pinned_globally": false,
    "pinned_at": "2026-01-07T16:27:16.979Z",
    "pinned_until": "3026-01-01T00:00:00.000Z",
    "unpinned": null,
    "pinned": true,
    "highest_post_number": 2,
    "deleted_by": null,
    "has_deleted": false,
    "bookmarked": false,
    "participant_count": 1,
    "queued_posts_count": 0,
    "thumbnails": null,
    "created_by": {
      "id": 1,
      "username": "xuxiaowei",
      "name": "徐晓伟",
      "avatar_template": "/user_avatar/xuxiaowei.io/xuxiaowei/{size}/8_2.png"
    },
    "last_poster": {
      "id": 1,
      "username": "xuxiaowei",
      "name": "徐晓伟",
      "avatar_template": "/user_avatar/xuxiaowei.io/xuxiaowei/{size}/8_2.png"
    },
    "can_vote": false,
    "vote_count": 0,
    "user_voted": false,
    "discourse_zendesk_plugin_zendesk_id": null,
    "discourse_zendesk_plugin_zendesk_url": "https://your-url.zendesk.com/agent/tickets/",
    "pending_posts": []
  }
}
